[
    {
        "book": "Proverbs",
        "chapter": "11",
        "verseStart": "8",
        "verseEnd": "8",
        "fav": false
    },
    {
        "book": "Proverbs",
        "chapter": "11",
        "verseStart": "29",
        "verseEnd": "29",
        "fav": false
    },
    {
        "book": "Proverbs",
        "chapter": "15",
        "verseStart": "15",
        "verseEnd": "16",
        "fav": false
    },
    {
        "book": "Proverbs",
        "chapter": "17",
        "verseStart": "3",
        "verseEnd": "3",
        "fav": false
    },
    {
        "book": "Proverbs",
        "chapter": "22",
        "verseStart": "5",
        "verseEnd": "5",
        "fav": false
    },
    {
        "book": "Proverbs",
        "chapter": "22",
        "verseStart": "5",
        "verseEnd": "5",
        "fav": false
    },
    {
        "book": "Proverbs",
        "chapter": "24",
        "verseStart": "10",
        "verseEnd": "10",
        "fav": false
    },
    {
        "book": "Proverbs",
        "chapter": "24",
        "verseStart": "16",
        "verseEnd": "17",
        "fav": false
    },
    {
        "book": "Proverbs",
        "chapter": "26",
        "verseStart": "2",
        "verseEnd": "2",
        "fav": false
    }
]